snapboost/__init__.py
snapboost/hnbm.py
snapboost/snapboost.py
snapboost/utils.py
snapboost-0.1.2.dist-info/LICENSE
snapboost-0.1.2.dist-info/METADATA
snapboost-0.1.2.dist-info/WHEEL
snapboost-0.1.2.dist-info/top_level.txt
snapboost-0.1.2.dist-info/RECORD
