Metadata-Version: 2.1
Name: snapboost
Version: 0.1.2
Summary: Heterogeneous Newton Boosting Machine
Home-page: https://github.com/samsonq/snapboost
Author: Samson Qian
Author-email: samsonqian@gmail.com
License: MIT
Keywords: boosting gradient-boosting snapboost
Platform: UNKNOWN
Requires-Python: >=3.6
License-File: LICENSE
